README.txt
setup.py
pyssher/__init__.py
pyssher/pyssher.py
pyssher.egg-info/PKG-INFO
pyssher.egg-info/SOURCES.txt
pyssher.egg-info/dependency_links.txt
pyssher.egg-info/requires.txt
pyssher.egg-info/top_level.txt
pyssher.egg-info/zip-safe