Metadata-Version: 1.1
Name: pyssher
Version: 1.0.26
Summary: ssh sftp...
Home-page: https://pypi.python.org/pypi/pyssher
Author: Andrew liu
Author-email: 1185978974@qq.com
License: GPL
Keywords: ssh python python3
Platform: UNKNOWN
Classifier: License :: OSI Approved :: MIT License
Classifier: Programming Language :: Python
Classifier: Intended Audience :: Developers
Classifier: Operating System :: OS Independent
